{"avatarID":"avtr_a6e685bd-5c93-42ef-9ab4-42667a4ea17a","avatarParameters":[{"enabled":false,"name":"spank_onEnter","type":1},{"enabled":false,"name":"SpankToggle","type":1},{"enabled":false,"name":"BellToggle","type":1},{"enabled":false,"name":"CuffsArmsToggle","type":1},{"enabled":false,"name":"CuffsLegsToggle","type":1},{"enabled":false,"name":"LeashToggle","type":1},{"enabled":false,"name":"CapToggle","type":1},{"enabled":false,"name":"TailToggle","type":1},{"enabled":false,"name":"CarrotCondomToggle","type":1},{"enabled":false,"name":"SoftpantsToggle","type":1},{"enabled":false,"name":"CarrotK9Toggle","type":1},{"enabled":false,"name":"RibbonsToggle","type":1},{"enabled":false,"name":"TailCollarToggle","type":1},{"enabled":false,"name":"CarrotErectToggle","type":1},{"enabled":false,"name":"EarTagToggle","type":1},{"enabled":false,"name":"LongerTopToggle","type":1},{"enabled":false,"name":"HarnessToggle","type":1},{"enabled":false,"name":"ShortsToggle","type":1},{"enabled":false,"name":"ShortTopToggle","type":1},{"enabled":false,"name":"SpunkToggle","type":1},{"enabled":false,"name":"GagToggle","type":1},{"enabled":false,"name":"BlindfoldToggle","type":1},{"enabled":false,"name":"SkirtTailToggle","type":1},{"enabled":false,"name":"SocksFullToggle","type":1},{"enabled":false,"name":"Gape","type":3},{"enabled":false,"name":"ScarfToggle","type":1},{"enabled":false,"name":"Dong2Toggle","type":1},{"enabled":false,"name":"ChestFluffToggle","type":1},{"enabled":false,"name":"TopToggle","type":1},{"enabled":false,"name":"BellyBulgeToggle","type":1},{"enabled":false,"name":"SkiGogglesToggle","type":1},{"enabled":false,"name":"UndiesToggle","type":1},{"enabled":false,"name":"SkirtToggle","type":1},{"enabled":false,"name":"PenetratorToggle","type":1},{"enabled":false,"name":"OrificeLeftFootToggle","type":1},{"enabled":false,"name":"OrificeRightHandToggle","type":1},{"enabled":false,"name":"OrificeLeftHandToggle","type":1},{"enabled":false,"name":"HoodieUpToggle","type":1},{"enabled":false,"name":"GlassesToggle","type":1},{"enabled":false,"name":"ArmwarmersToggle","type":1},{"enabled":false,"name":"SocksToggle","type":1},{"enabled":false,"name":"CrownToggle","type":1},{"enabled":false,"name":"OrificeButtToggle","type":1},{"enabled":false,"name":"OrificeMouthToggle","type":1},{"enabled":false,"name":"TailV","type":3},{"enabled":false,"name":"LegwarmersToggle","type":1},{"enabled":false,"name":"CollarToggle","type":1}]}